{
  "animals": [
    {
      "id": 1,
      "name": "Poodles",
      "breed": "Poodle",
      "locationId": 1,
      "customerId": 1
    },
    {
      "id": 2,
      "name": "Decker",
      "breed": "German Shepherd",
      "customerId": 1,
      "locationId": 1
    },
    {
      "name": "Ray",
      "breed": "Lab",
      "locationId": 1,
      "customerId": 2,
      "id": 3
    }
  ],
  "customers": [
    {
      "id": 1,
      "name": "Hannah Hall",
      "address": "7002 Chestnut Ct",
      "email": "h@h.com"
    },
    {
      "id": 2,
      "name": "Bill Nye",
      "address": "7002 Chestnut Ct",
      "email": "b@b.com"
    },
    {
      "email": "MickeyDs@home.com",
      "name": "Ronald McDonald",
      "id": 3
    }
  ],
  "owners": [
    {
      "id": 1,
      "name": "Chuck Norris",
      "phoneNumber": "(555)123-7890"
    },
    {
      "id": 2,
      "name": "Cody Jones",
      "phoneNumber": "(555)456-7890"
    }
  ],
  "employees": [
    {
      "id": 1,
      "name": "Chuck Norris"
    },
    {
      "id": 3,
      "name": "Henry Cavill"
    }
  ],
  "locations": [
    {
      "id": 1,
      "name": "Nashville North",
      "address": "8422 Johnson Pike"
    },
    {
      "id": 2,
      "name": "Nashville South",
      "address": "5272 Davidson Lane"
    }
  ]
}